{
    "name": "Monster Grapple 2",
    "description": "",
    "dependencies": {
        "device": "*",
        "arcade-fancy-text": "github:riknoll/arcade-fancy-text#v0.1.0",
        "Declutter": "github:S0m3randomguy/declutter#6b0626bf1bd2c7d9a70b846031b5226e48ee932a",
        "Timers": "github:microsoft/arcade-timers#v1.1.0"
    },
    "files": [
        "main.blocks",
        "main.ts",
        "README.md",
        "assets.json",
        "images.g.jres",
        "images.g.ts"
    ],
    "testFiles": [
        "test.ts"
    ],
    "targetVersions": {
        "target": "1.12.51",
        "targetId": "arcade"
    },
    "supportedTargets": [
        "arcade"
    ],
    "preferredEditor": "blocksprj"
}
